samoyed/__init__.py
samoyed/api_gateway.py
samoyed-0.1.0.dev1.dist-info/WHEEL
samoyed-0.1.0.dev1.dist-info/METADATA
samoyed-0.1.0.dev1.dist-info/RECORD
